{
	"brands": null,
	"cacheVersn": 0,
	"defaultIncidentType": "",
	"definitionId": "",
	"description": "",
	"feed": true,
	"fromServerVersion": "",
	"id": "b38d76d9-47d8-4c20-894e-4b34f106481a",
	"incidentSamples": null,
	"indicatorSamples": null,
	"instanceIds": null,
	"itemVersion": "",
	"keyTypeMap": {},
	"locked": false,
	"logicalVersion": 0,
	"mapping": null,
	"name": "e_e_e_e_e",
	"nameRaw": "e_e_e_e_e",
	"packID": "",
	"packName": "",
	"propagationLabels": [
		"all"
	],
	"sourceClassifierId": "",
	"system": false,
	"toServerVersion": "",
	"transformer": {},
	"type": "mapping-incoming",
	"unclassifiedCases": null,
	"version": -1
}