{
	"brands": null,
	"cacheVersn": 0,
	"defaultIncidentType": "",
	"definitionId": "",
	"description": "",
	"feed": true,
	"fromServerVersion": "",
	"id": "02bf9376-0c97-4362-8b5a-460ef3aabe7f",
	"incidentSamples": null,
	"indicatorSamples": null,
	"instanceIds": null,
	"itemVersion": "",
	"keyTypeMap": {},
	"locked": false,
	"logicalVersion": 0,
	"mapping": null,
	"name": "c_c_c",
	"nameRaw": "c_c_c",
	"packID": "",
	"packName": "",
	"propagationLabels": [
		"all"
	],
	"sourceClassifierId": "",
	"system": false,
	"toServerVersion": "",
	"transformer": {},
	"type": "classification",
	"unclassifiedCases": null,
	"version": -1
}